{
  "metadata": {
    "generatedAt": "2026-05-27T12:32:30.491Z",
    "source": "brain/runtime/run-runtime-benchmark.ts",
    "sourceHash": "3aa2887a9ecde2983215c85a9f39ced96e0a85415e8ef542806292e4f6482c23",
    "url": "http://127.0.0.1:3000",
    "eventCount": 59,
    "confidence": 0.82
  },
  "propagation": [
    {
      "state": "messages",
      "timestamp": 179.5999999642372,
      "nextRender": "route:study",
      "lagMs": 11.5,
      "metadata": {
        "previousType": "object",
        "nextType": "object"
      }
    },
    {
      "state": "pricing",
      "timestamp": 213.69999998807907,
      "nextRender": "route:study",
      "lagMs": 4.399999976158142,
      "metadata": {
        "previousType": "object",
        "nextType": "object"
      }
    },
    {
      "state": "activeLearningBookId",
      "timestamp": 242.5,
      "nextRender": "route:study",
      "lagMs": 7.5,
      "metadata": {
        "previousType": "object",
        "nextType": "string"
      }
    },
    {
      "state": "activeView",
      "timestamp": 1367.0999999642372,
      "nextRender": "route:study",
      "lagMs": 7.800000011920929,
      "metadata": {
        "previousType": "string",
        "nextType": "string"
      }
    },
    {
      "state": "activeView",
      "timestamp": 2726.300000011921,
      "nextRender": "route:brain",
      "lagMs": 4.399999976158142,
      "metadata": {
        "previousType": "string",
        "nextType": "string"
      }
    },
    {
      "state": "activeView",
      "timestamp": 3598.300000011921,
      "nextRender": "route:analytics",
      "lagMs": 3.899999976158142,
      "metadata": {
        "previousType": "string",
        "nextType": "string"
      }
    },
    {
      "state": "activeView",
      "timestamp": 4406.800000011921,
      "nextRender": "route:revision",
      "lagMs": 6.099999964237213,
      "metadata": {
        "previousType": "string",
        "nextType": "string"
      }
    },
    {
      "state": "pricing",
      "timestamp": 4775,
      "nextRender": "route:study",
      "lagMs": 3.399999976158142,
      "metadata": {
        "previousType": "object",
        "nextType": "object"
      }
    }
  ]
}
