{
  "metadata": {
    "generatedAt": "2026-05-27T14:07:19.492Z",
    "source": "brain/runtime/run-runtime-benchmark.ts",
    "sourceHash": "aaaad77e48968790695157df7ea1695dd50cfdb9ef5b774dc1b07c903e8b3b2d",
    "url": "http://127.0.0.1:3000",
    "eventCount": 44,
    "confidence": 0.82
  },
  "renders": [
    {
      "component": "route:study",
      "count": 14,
      "totalDurationMs": 109.09999984502792,
      "maxDurationMs": 37.799999952316284,
      "averageDurationMs": 7.7928571317877084
    },
    {
      "component": "route:analytics",
      "count": 15,
      "totalDurationMs": 108.99999988079071,
      "maxDurationMs": 23.5,
      "averageDurationMs": 7.266666658719381
    },
    {
      "component": "route:revision",
      "count": 5,
      "totalDurationMs": 27.600000023841858,
      "maxDurationMs": 9.300000011920929,
      "averageDurationMs": 5.520000004768372
    }
  ]
}
